doc81/__init__.py
doc81/core/config.py
doc81/core/database.py
doc81/core/exception.py
doc81/core/models.py
doc81/core/schema.py
doc81/mcp/cli.py
doc81/mcp/main.py
doc81/rest/app.py
doc81/rest/routes/companies.py
doc81/rest/routes/health.py
doc81/rest/routes/templates.py
doc81/rest/routes/users.py
doc81/service/__init__.py
doc81/service/generate_template.py
doc81/service/get_template.py
doc81/service/list_templates.py
doc81/service/templatify.py
doc81/service/prompts/doc81-generate.md
doc81-0.1.6.dist-info/METADATA
doc81-0.1.6.dist-info/WHEEL
doc81-0.1.6.dist-info/entry_points.txt
doc81-0.1.6.dist-info/licenses/LICENSE
doc81-0.1.6.dist-info/RECORD
