Metadata-Version: 2.4
Name: doc81
Version: 0.1.6
Summary: A tool to help you write better documentation
License-File: LICENSE
Classifier: Development Status :: 3 - Alpha
Classifier: Intended Audience :: Developers
Classifier: License :: OSI Approved :: MIT License
Classifier: Programming Language :: Python :: 3
Classifier: Programming Language :: Python :: 3.10
Classifier: Programming Language :: Python :: 3.11
Classifier: Programming Language :: Python :: 3.12
Classifier: Programming Language :: Python :: 3.13
Classifier: Topic :: Documentation
Classifier: Topic :: Documentation :: Sphinx
Classifier: Topic :: Software Development :: Documentation
Requires-Python: >=3.10
Requires-Dist: fastapi>=0.115.14
Requires-Dist: fastmcp>=2.9.2
Requires-Dist: litellm>=1.73.6
Requires-Dist: mistune>=3.1.3
Requires-Dist: psycopg2-binary>=2.9.10
Requires-Dist: pydantic-settings>=2.10.1
Requires-Dist: pydantic>=2.11.7
Requires-Dist: python-frontmatter>=1.1.0
Requires-Dist: sqlalchemy>=2.0.41
Requires-Dist: typer>=0.16.0
